{
    "mapImage": "Map Dewlight Pavilion Floor 1.png",
    "pageCategories": [],
    "defaultSort": "",
    "description": "{{Stub|Missing enemy lists and location context for treasures}}\n{{Map Description|Dewlight Pavilion|Floor 1}}",
    "coordinateOrder": "xy",
    "mapBounds": [
        [
            0,
            0
        ],
        [
            1400,
            1400
        ]
    ],
    "origin": "top-left",
    "useMarkerClustering": false,
    "categories": [
        {
            "id": "space_anchors",
            "listId": 1,
            "name": "Space Anchors",
            "color": "#fa005a",
            "symbol": "",
            "symbolColor": "",
            "icon": "File:Icon Space Anchor Active.png"
        },
        {
            "id": "event_waypoints",
            "listId": 2,
            "name": "Events",
            "color": "#fa005a",
            "symbol": "",
            "symbolColor": "",
            "icon": "File:Icon Map Event.png"
        },
        {
            "color": "#fa005a",
            "symbol": "",
            "symbolColor": "",
            "id": "marked_locations",
            "name": "Marked Locations",
            "icon": "File:Icon Map Major Landmark.png",
            "listId": 3
        },
        {
            "color": "#fa005a",
            "symbol": "",
            "symbolColor": "",
            "id": "event_locations",
            "name": "Marked Event Locations",
            "icon": "File:Icon Map Event.png",
            "listId": 4
        },
        {
            "color": "#fa005a",
            "symbol": "",
            "symbolColor": "",
            "id": "calyx_golden",
            "name": "Calyx (Golden)",
            "icon": "File:Icon Calyx Golden.png",
            "listId": 5
        },
        {
            "color": "#fa005a",
            "symbol": "",
            "symbolColor": "",
            "id": "calyx_crimson",
            "name": "Calyx (Crimson)",
            "icon": "File:Icon Calyx Crimson.png",
            "listId": 6
        },
        {
            "color": "#fa005a",
            "symbol": "",
            "symbolColor": "",
            "id": "caverns",
            "name": "Caverns of Corrosion",
            "icon": "File:Icon Cavern of Corrosion.png",
            "listId": 7
        },
        {
            "color": "#fa005a",
            "symbol": "",
            "symbolColor": "",
            "id": "echo_of_war",
            "name": "Echo of War",
            "icon": "File:Icon Echo of War Enemy.png",
            "listId": 8
        },
        {
            "color": "#fa005a",
            "symbol": "",
            "symbolColor": "",
            "id": "stagnant_shadows",
            "name": "Stagnant Shadows",
            "icon": "File:Icon Stagnant Shadow.png",
            "listId": 9
        },
        {
            "id": "basic_treasures",
            "listId": 10,
            "name": "Basic Treasures",
            "color": "#fa005a",
            "symbol": "",
            "symbolColor": "",
            "icon": "File:Icon Map Basic Treasure.png"
        },
        {
            "id": "bountiful_treasures",
            "listId": 11,
            "name": "Bountiful Treasures",
            "color": "#fa005a",
            "symbol": "",
            "symbolColor": "",
            "icon": "File:Icon Map Bountiful Treasure.png"
        },
        {
            "id": "precious_treasures",
            "listId": 12,
            "name": "Precious Treasures",
            "color": "#fa005a",
            "symbol": "",
            "symbolColor": "",
            "icon": "File:Icon Map Precious Treasure.png"
        },
        {
            "color": "#fa005a",
            "symbol": "",
            "symbolColor": "",
            "id": "warp_trotters",
            "name": "Warp Trotters",
            "icon": "File:Icon Map Warp Trotter.png",
            "listId": 13
        },
        {
            "id": "lordly_trashcans",
            "listId": 14,
            "name": "Lordly Trashcans",
            "color": "#555e6a",
            "symbol": "🗑",
            "symbolColor": "#fff",
            "icon": "File:Icon Map Lordly Trashcan.png"
        },
        {
            "id": "puzzles",
            "listId": 15,
            "name": "Puzzles",
            "color": "#fa005a",
            "symbol": "",
            "symbolColor": "",
            "icon": "File:Icon Map Puzzle.png"
        },
        {
            "id": "origami_birds",
            "listId": 16,
            "name": "Origami Birds",
            "color": "#fa005a",
            "symbol": "",
            "symbolColor": "",
            "icon": "File:Icon Map Origami Bird.png"
        },
        {
            "id": "great_tree",
            "listId": 17,
            "name": "Origami Bird \"Great Tree\"",
            "color": "#fa005a",
            "symbol": "",
            "symbolColor": "",
            "icon": "File:Icon Map Origami Bird Tree.png"
        },
        {
            "id": "dreamscape_pass_stickers",
            "listId": 18,
            "name": "Dreamscape Pass Stickers",
            "color": "#fa005a",
            "symbol": "",
            "symbolColor": "",
            "icon": "File:Icon Map Sticker.png"
        },
        {
            "id": "hanu",
            "listId": 19,
            "name": "Hanu's Adventure",
            "color": "#fa005a",
            "symbol": "",
            "symbolColor": "",
            "icon": "File:Icon Map Hanu.png"
        },
        {
            "id": "enemies",
            "listId": 20,
            "name": "Enemies",
            "color": "#fa005a",
            "symbol": "",
            "symbolColor": "",
            "icon": "File:Icon Map Enemy.png"
        },
        {
            "id": "trailblaze_missions",
            "listId": 21,
            "name": "Trailblaze Missions",
            "color": "#fa005a",
            "symbol": "",
            "symbolColor": "",
            "icon": "File:Icon Map Trailblaze Mission.png"
        },
        {
            "color": "#fa005a",
            "symbol": "",
            "symbolColor": "",
            "id": "trailblaze_mission_steps",
            "name": "Trailblaze Mission Steps",
            "icon": "File:Icon Map Trailblaze Mission Step.png",
            "listId": 22
        },
        {
            "id": "trailblaze_continuances",
            "listId": 23,
            "name": "Trailblaze Continuances",
            "color": "#fa005a",
            "symbol": "",
            "symbolColor": "",
            "icon": "File:Icon Map Trailblaze Continuance.png"
        },
        {
            "color": "#fa005a",
            "symbol": "",
            "symbolColor": "",
            "id": "trailblaze_continuance_steps",
            "name": "Trailblaze Continuance Steps",
            "icon": "File:Icon Map Trailblaze Continuance Step.png",
            "listId": 24
        },
        {
            "id": "companion_missions",
            "listId": 25,
            "name": "Companion Missions",
            "color": "#fa005a",
            "symbol": "",
            "symbolColor": "",
            "icon": "File:Icon Map Companion Mission.png"
        },
        {
            "color": "#fa005a",
            "symbol": "",
            "symbolColor": "",
            "id": "companion_mission_steps",
            "name": "Companion Mission Steps",
            "icon": "File:Icon Map Companion Mission Step.png",
            "listId": 26
        },
        {
            "id": "daily_missions",
            "listId": 27,
            "name": "Daily Missions",
            "color": "#fa005a",
            "symbol": "",
            "symbolColor": "",
            "icon": "File:Icon Map Daily Mission.png"
        },
        {
            "color": "#fa005a",
            "symbol": "",
            "symbolColor": "",
            "id": "daily_mission_steps",
            "name": "Daily Mission Steps",
            "icon": "File:Icon Map Daily Mission Step.png",
            "listId": 28
        },
        {
            "id": "adventure_missions",
            "listId": 29,
            "name": "Adventure Missions",
            "color": "#fa005a",
            "symbol": "",
            "symbolColor": "",
            "icon": "File:Icon Map Adventure Mission.png"
        },
        {
            "color": "#fa005a",
            "symbol": "",
            "symbolColor": "",
            "id": "adventure_mission_steps",
            "name": "Adventure Mission Steps",
            "icon": "File:Icon Map Adventure Mission Step.png",
            "listId": 30
        },
        {
            "id": "shops",
            "listId": 31,
            "name": "Shops",
            "color": "#fa005a",
            "symbol": "",
            "symbolColor": "",
            "icon": "File:Icon Map Shop.png"
        },
        {
            "id": "shops_with_collectibles",
            "listId": 32,
            "name": "Shops with Collectibles",
            "color": "#fa005a",
            "symbol": "",
            "symbolColor": "",
            "icon": "File:Icon Map Shop With Collectibles.png"
        },
        {
            "id": "exits",
            "listId": 33,
            "name": "Exit",
            "color": "#fa005a",
            "symbol": "",
            "symbolColor": "",
            "icon": "File:Icon Map Exit.png"
        },
        {
            "id": "entrances",
            "listId": 34,
            "name": "Entrance",
            "color": "#fa005a",
            "symbol": "",
            "symbolColor": "",
            "icon": "File:Icon Map Entrance.png"
        },
        {
            "color": "#fa005a",
            "symbol": "",
            "symbolColor": "",
            "id": "subareas_with_collectibles",
            "name": "Subareas with Collectibles",
            "icon": "File:Icon Map Entrance With Collectibles.png",
            "listId": 35
        },
        {
            "id": "dreamwalker_rooms",
            "listId": 36,
            "name": "Dreamwalker Rooms",
            "color": "#fa005a",
            "symbol": "",
            "symbolColor": "",
            "icon": "File:Icon Map 3D.png"
        },
        {
            "id": "arcane_artworks",
            "listId": 37,
            "name": "Arcane Artworks",
            "color": "#fa005a",
            "symbol": "",
            "symbolColor": "",
            "icon": "File:Icon Map Frame Portal.png"
        },
        {
            "id": "npcs",
            "listId": 38,
            "name": "Other NPCs",
            "color": "#fa005a",
            "symbol": "",
            "symbolColor": "",
            "icon": "File:Icon Map NPC.png"
        },
        {
            "id": "readables",
            "listId": 39,
            "name": "Readables",
            "color": "#ffffff",
            "symbol": "📚",
            "symbolColor": "#000",
            "icon": "File:Icon Map Readable.png"
        },
        {
            "id": "phonograph_records",
            "listId": 40,
            "name": "Phonograph Records",
            "color": "#ffffff",
            "symbol": "📚",
            "symbolColor": "#000",
            "icon": "File:Icon Map Phonograph.png"
        },
        {
            "id": "achievements",
            "listId": 41,
            "name": "Achievements",
            "color": "#fa005a",
            "symbol": "🏆",
            "symbolColor": "#fff",
            "icon": "File:Icon Map Achievement.png"
        },
        {
            "id": "clockwork_gears",
            "listId": 42,
            "name": "Clockwork - Gears",
            "color": "#5d5d5d",
            "symbol": "",
            "symbolColor": "",
            "icon": "File:Icon Map Clockwork.png"
        },
        {
            "id": "clockwork_npcs",
            "listId": 43,
            "name": "Clockwork - NPCs",
            "color": "#5d5d5d",
            "symbol": "",
            "symbolColor": "",
            "icon": "File:Icon Map Psychic Detective.png"
        },
        {
            "id": "clockwork_bloodhounds_watchlist",
            "listId": 44,
            "name": "Clockwork - Bloodhound's Watchlist",
            "color": "#fa005a",
            "symbol": "",
            "symbolColor": "",
            "icon": "File:Icon Map Absorb Emotions.png"
        },
        {
            "color": "#fa005a",
            "symbol": "",
            "symbolColor": "",
            "id": "hound_statues",
            "name": "Hound Statues",
            "icon": "File:Icon Map Achievement.png",
            "worlds": [
                "penacony"
            ],
            "listId": 45
        },
        {
            "color": "#fa005a",
            "symbol": "",
            "symbolColor": "",
            "id": "warring_expeditions",
            "name": "Warring Expeditions",
            "icon": "File:Icon Map Warring Expedition.png",
            "listId": 46
        },
        {
            "color": "#fa005a",
            "symbol": "",
            "symbolColor": "",
            "id": "expeditions_with_collectibles",
            "name": "Warring Expeditions with Collectibles",
            "icon": "File:Icon Map Warring Expedition With Collectibles.png",
            "listId": 47
        },
        {
            "id": "investigations",
            "listId": 48,
            "name": "Investigations",
            "color": "#fa005a",
            "symbol": "",
            "symbolColor": "",
            "icon": "File:Icon Map Investigation.png"
        },
        {
            "color": "#fa005a",
            "symbol": "",
            "symbolColor": "",
            "id": "landmarks",
            "name": "Landmarks",
            "icon": "File:Icon Map Major Landmark.png",
            "listId": 49
        },
        {
            "id": "removed_event_waypoints",
            "listId": 50,
            "name": "Removed Events",
            "color": "#fa005a",
            "symbol": "",
            "symbolColor": "",
            "icon": "File:Icon Map Removed Event.png"
        },
        {
            "color": "#fa005a",
            "symbol": "",
            "symbolColor": "",
            "id": "dreamjolt_tv_stages",
            "name": "Dreamjolt TV",
            "icon": "File:Icon Map Television.png",
            "worlds": [
                "penacony"
            ],
            "listId": 51
        }
    ],
    "markers": [
        {
            "categoryId": "origami_birds",
            "position": [
                617.6666259765625,
                634.0196767942984
            ],
            "popup": {
                "title": "Origami Bird",
                "description": "",
                "link": {
                    "label": "Origami Bird",
                    "url": "Origami_Bird"
                }
            },
            "id": "i2114"
        },
        {
            "categoryId": "basic_treasures",
            "position": [
                759.4634863911745,
                193.64117636296987
            ],
            "popup": {
                "title": "Basic Treasure",
                "description": ""
            },
            "id": "i2113"
        },
        {
            "categoryId": "great_tree",
            "position": [
                721.9620456254274,
                561.6314054871694
            ],
            "popup": {
                "title": "Origami Bird \"Great Tree\"",
                "description": "",
                "link": {
                    "label": "Origami Bird \"Great Tree\"",
                    "url": "Origami_Bird_\"Great_Tree\""
                }
            },
            "id": "i2112"
        },
        {
            "categoryId": "space_anchors",
            "position": [
                639.5000758297762,
                596.9997078475674
            ],
            "popup": {
                "title": "Dreammaster Hall",
                "description": "The spacious main hall of the residence. The leaders of the five major lineages regularly gather to discuss the situation and plan for the Dreamscape. A finely crafted city sandpit is placed at the center of the hall.",
                "link": {
                    "label": "Dreammaster Hall",
                    "url": "Dreammaster_Hall"
                }
            },
            "id": "i2111"
        },
        {
            "categoryId": "lordly_trashcans",
            "position": [
                584.9621972849798,
                386.1257572068064
            ],
            "popup": {
                "title": "Lordly Trashcan",
                "description": "",
                "link": {
                    "label": "Lordly Trashcan",
                    "url": "Lordly_Trashcan"
                }
            },
            "id": "i2110"
        },
        {
            "categoryId": "origami_birds",
            "position": [
                613.0001895744404,
                358.49974030894873
            ],
            "popup": {
                "title": "Origami Bird",
                "description": "",
                "link": {
                    "label": "Origami Bird",
                    "url": "Origami_Bird"
                }
            },
            "id": "i2109"
        },
        {
            "categoryId": "origami_birds",
            "position": [
                1040.4657991993477,
                668.6260168978575
            ],
            "popup": {
                "title": "Origami Bird",
                "description": "",
                "link": {
                    "label": "Origami Bird",
                    "url": "Origami_Bird"
                }
            },
            "id": "i2108"
        },
        {
            "categoryId": "basic_treasures",
            "position": [
                979.4628039231891,
                671.1272504303506
            ],
            "popup": {
                "title": "Basic Treasure",
                "description": ""
            },
            "id": "i2107"
        },
        {
            "categoryId": "basic_treasures",
            "position": [
                788.001402850859,
                352.99944815651634
            ],
            "popup": {
                "title": "Basic Treasure",
                "description": ""
            },
            "id": "i2106"
        },
        {
            "categoryId": "enemies",
            "position": [
                1039,
                607.9606464114032
            ],
            "popup": {
                "title": "Memory Zone Meme \"Allseer\"",
                "description": "",
                "link": {
                    "label": "Memory Zone Meme \"Allseer\"",
                    "url": "Memory_Zone_Meme_\"Allseer\""
                }
            },
            "id": "i2014",
            "icon": "File:Icon Enemy Memory Zone Meme Allseer.png"
        },
        {
            "categoryId": "enemies",
            "position": [
                1016.5,
                595.9382864178824
            ],
            "popup": {
                "title": "Memory Zone Meme \"Something In The Mirror\"",
                "description": "",
                "link": {
                    "label": "Memory Zone Meme \"Something In The Mirror\"",
                    "url": "Memory_Zone_Meme_\"Something_In_The_Mirror\""
                }
            },
            "id": "i2013",
            "icon": "File:Icon Enemy Memory Zone Meme Something In The Mirror.png"
        },
        {
            "categoryId": "enemies",
            "position": [
                973.5,
                600.4588576119215
            ],
            "popup": {
                "title": "Memory Zone Meme \"Heartbreaker\"",
                "description": "",
                "link": {
                    "label": "Memory Zone Meme \"Heartbreaker\"",
                    "url": "Memory_Zone_Meme_\"Heartbreaker\""
                }
            },
            "id": "i2012",
            "icon": "File:Icon Enemy Memory Zone Meme Heartbreaker.png"
        },
        {
            "categoryId": "enemies",
            "position": [
                956.5,
                610.9521496138652
            ],
            "popup": {
                "title": "Memory Zone Meme \"Allseer\"",
                "description": "",
                "link": {
                    "label": "Memory Zone Meme \"Allseer\"",
                    "url": "Memory_Zone_Meme_\"Allseer\""
                }
            },
            "id": "i2011",
            "icon": "File:Icon Enemy Memory Zone Meme Allseer.png"
        },
        {
            "categoryId": "entrances",
            "position": [
                706.5,
                590
            ],
            "icon": "File:Icon Map Special Subarea.png",
            "popup": {
                "title": "City Sandpit",
                "description": "A cityscape sandpit made in the image of Penacony with a 1:100 ratio to the real deal. It's easy to imagine a scene of the family heads using it to plan and make comments.",
                "link": {
                    "url": "Map:City_Sandpit",
                    "label": "City Sandpit"
                }
            },
            "id": "1"
        },
        {
            "categoryId": "readables",
            "position": [
                656,
                202.5
            ],
            "icon": "File:Icon Map Penacony Readable 3.png",
            "popup": {
                "title": "Classified: Major Incidents in Dreamscape",
                "description": "",
                "link": {
                    "url": "Classified:_Major_Incidents_in_Dreamscape",
                    "label": "Classified: Major Incidents in Dreamscape"
                }
            },
            "id": "2"
        },
        {
            "categoryId": "npcs",
            "position": [
                630.0321420372139,
                156.90627867404942
            ],
            "popup": {
                "title": "Mr. McCoy",
                "description": "",
                "link": {
                    "url": "Mr._McCoy",
                    "label": "Mr. McCoy"
                }
            },
            "id": "3"
        },
        {
            "categoryId": "adventure_missions",
            "position": [
                630.3856954278071,
                156.19917189286275
            ],
            "popup": {
                "title": "Clockwork: Mr. McCoy",
                "description": "Adventure Mission start location",
                "link": {
                    "url": "Clockwork:_Mr._McCoy",
                    "label": "Clockwork: Mr. McCoy"
                }
            },
            "id": "4"
        },
        {
            "categoryId": "dreamscape_pass_stickers",
            "position": [
                718.4204896855324,
                63.21463016683174
            ],
            "popup": {
                "title": "Maeven Ellis",
                "description": "",
                "link": {
                    "url": "Maeven_Ellis_(Dreamscape_Pass_Sticker)",
                    "label": "Maeven Ellis (Dreamscape Pass Sticker)"
                }
            },
            "id": "5"
        },
        {
            "categoryId": "readables",
            "position": [
                718.7740430761256,
                63.21463016683174
            ],
            "icon": "File:Icon Map Penacony Readable 2.png",
            "popup": {
                "title": "Planet of Festivities: Maeven Ellis",
                "description": "",
                "link": {
                    "url": "Planet_of_Festivities_Collectible_Card",
                    "label": "Planet of Festivities Collectible Card"
                }
            },
            "id": "6"
        },
        {
            "categoryId": "readables",
            "position": [
                723.0166837632449,
                144.88546339387813
            ],
            "icon": "File:Icon Map Penacony Readable 1.png",
            "popup": {
                "title": "Watchmaker Investigation Record",
                "description": "",
                "link": {
                    "url": "Watchmaker_Investigation_Record",
                    "label": "Watchmaker Investigation Record"
                }
            },
            "id": "7"
        }
    ]
}